setup.cfg
setup.py
imgii/__init__.py
imgii.egg-info/PKG-INFO
imgii.egg-info/SOURCES.txt
imgii.egg-info/dependency_links.txt
imgii.egg-info/entry_points.txt
imgii.egg-info/requires.txt
imgii.egg-info/top_level.txt