Metadata-Version: 1.1
Name: imgii
Version: 0.3.1
Summary: Very simple conversion of images to text.
Home-page: https://github.com/spurll/imgii
Author: Gem Newman
Author-email: spurll@gmail.com
License: MPL2
Download-URL: https://github.com/spurll/imgii/tarball/0.3.1
Keywords: ascii,image
Platform: UNKNOWN
Classifier: Topic :: Scientific/Engineering :: Image Recognition
Classifier: Topic :: Multimedia :: Graphics :: Graphics Conversion
Classifier: Programming Language :: Python
Classifier: Intended Audience :: End Users/Desktop
Classifier: Intended Audience :: Developers
Classifier: Environment :: Console
Classifier: Development Status :: 4 - Beta
Classifier: License :: OSI Approved :: Mozilla Public License 2.0 (MPL 2.0)
